[{"id":"news_1","type":"info","title":"Local Traffic Advisory","message":"Road construction on Main Street causing delays. Alternative routes recommended.","timestamp":"2025-10-24 00:13:33","status":"active","source":"news","priority":"medium","url":"#"},{"id":"news_2","type":"info","title":"Community Health Update","message":"Free health screening available at the barangay health center this weekend.","timestamp":"2025-10-23 22:13:33","status":"active","source":"news","priority":"low","url":"#"},{"id":"news_3","type":"emergency","title":"Power Interruption Notice","message":"Scheduled power maintenance on October 15, 2025 from 8:00 AM to 12:00 PM.","timestamp":"2025-10-23 20:13:33","status":"active","source":"news","priority":"high","url":"#"}]